{
  "$schema": "http://json-schema.org/draft-07/schema",
  "title": "TWA Bubblewrap Configuration",
  "description": "Schema and reference for android/twa-manifest.json generated by Bubblewrap CLI",
  "type": "object",
  "required": [
    "packageId",
    "host",
    "startUrl",
    "name",
    "launcherName",
    "display",
    "themeColor",
    "backgroundColor",
    "minSdkVersion",
    "targetSdkVersion",
    "signingKey"
  ],
  "properties": {
    "packageId": {
      "type": "string",
      "description": "Reverse-domain package name. IMMUTABLE after first Play Store publication.",
      "example": "com.graditone.app"
    },
    "host": {
      "type": "string",
      "description": "Production domain of the PWA (no scheme, no trailing slash). Must match the domain where assetlinks.json is hosted.",
      "example": "graditone.com"
    },
    "startUrl": {
      "type": "string",
      "description": "Path relative to host. Must match PWA start_url.",
      "example": "/"
    },
    "name": {
      "type": "string",
      "maxLength": 30,
      "description": "Full app name shown on Play Store.",
      "example": "Graditone"
    },
    "launcherName": {
      "type": "string",
      "maxLength": 12,
      "description": "Short name shown under home screen icon.",
      "example": "Graditone"
    },
    "display": {
      "type": "string",
      "enum": ["standalone", "fullscreen"],
      "description": "Must match PWA manifest display mode."
    },
    "orientation": {
      "type": "string",
      "enum": ["default", "portrait", "landscape"],
      "description": "Screen orientation lock."
    },
    "themeColor": {
      "type": "string",
      "pattern": "^#[0-9a-fA-F]{6}$",
      "description": "Status bar colour. Must match PWA manifest theme_color.",
      "example": "#6366f1"
    },
    "backgroundColor": {
      "type": "string",
      "pattern": "^#[0-9a-fA-F]{6}$",
      "description": "Splash screen background. Must match PWA manifest background_color.",
      "example": "#1a1a1a"
    },
    "enableNotifications": {
      "type": "boolean",
      "description": "Whether to request notification permission. Set false for initial release.",
      "default": false
    },
    "minSdkVersion": {
      "type": "integer",
      "minimum": 28,
      "description": "Minimum Android API level. 28 = Android 9.0.",
      "example": 28
    },
    "targetSdkVersion": {
      "type": "integer",
      "minimum": 34,
      "description": "Target Android API level. Play Store requires targetSdk >= 34 for all new apps.",
      "example": 34
    },
    "signingKey": {
      "type": "object",
      "description": "Signing key reference. Actual keystore stored as CI secret, not committed.",
      "required": ["alias"],
      "properties": {
        "alias": {
          "type": "string",
          "description": "Keystore alias for the signing certificate.",
          "example": "graditone-release"
        }
      }
    },
    "features": {
      "type": "object",
      "description": "Optional TWA feature flags.",
      "properties": {
        "locationDelegation": { "type": "object" },
        "playBilling": { "type": "object" }
      }
    },
    "iconUrl": {
      "type": "string",
      "description": "URL or path to the maskable 512x512 icon used for Play Store upload.",
      "example": "https://graditone.com/icons/icon-512x512.png"
    }
  },
  "examples": [
    {
      "packageId": "com.graditone.app",
      "host": "graditone.com",
      "startUrl": "/",
      "name": "Graditone",
      "launcherName": "Graditone",
      "display": "standalone",
      "orientation": "default",
      "themeColor": "#6366f1",
      "backgroundColor": "#1a1a1a",
      "enableNotifications": false,
      "minSdkVersion": 28,
      "targetSdkVersion": 34,
      "signingKey": {
        "alias": "graditone-release"
      }
    }
  ]
}
